DASH/DASH.py
DASH/__init__.py
dash_pytorch-0.0.3.dist-info/METADATA
dash_pytorch-0.0.3.dist-info/WHEEL
dash_pytorch-0.0.3.dist-info/licenses/LICENSE
dash_pytorch-0.0.3.dist-info/RECORD
