Metadata-Version: 2.4
Name: DASH-pytorch
Version: 0.0.3
Summary: DASH
Project-URL: Homepage, https://pypi.org/project/DASH/
Project-URL: Repository, https://github.com/lucidrains/DASH
Author-email: Phil Wang <lucidrains@gmail.com>
License: MIT License
License-File: LICENSE
Keywords: artificial intelligence,continual learning,deep learning,plasticity
Classifier: Development Status :: 4 - Beta
Classifier: Intended Audience :: Developers
Classifier: License :: OSI Approved :: MIT License
Classifier: Programming Language :: Python :: 3.9
Classifier: Topic :: Scientific/Engineering :: Artificial Intelligence
Requires-Python: >=3.9
Requires-Dist: einops>=0.8.1
Requires-Dist: torch>=2.4
Provides-Extra: examples
Provides-Extra: test
Requires-Dist: pytest; extra == 'test'
